tractosearch/__init__.py
tractosearch/binning.py
tractosearch/group.py
tractosearch/io.py
tractosearch/length.py
tractosearch/resampling.py
tractosearch/search.py
tractosearch/transform.py
tractosearch/util.py
tractosearch-0.0.1a5.dist-info/LICENSE
tractosearch-0.0.1a5.dist-info/METADATA
tractosearch-0.0.1a5.dist-info/WHEEL
tractosearch-0.0.1a5.dist-info/top_level.txt
tractosearch-0.0.1a5.dist-info/RECORD
